mdformat_gherkin/__init__.py
mdformat_gherkin-0.1.0.dist-info/entry_points.txt
mdformat_gherkin-0.1.0.dist-info/licenses/LICENSE
mdformat_gherkin-0.1.0.dist-info/WHEEL
mdformat_gherkin-0.1.0.dist-info/METADATA
mdformat_gherkin-0.1.0.dist-info/RECORD
