Metadata-Version: 2.4
Name: mdformat-gherkin
Version: 0.1.0
Summary: Mdformat plugin to format Gherkin code blocks using reformat-gherkin
Keywords: mdformat,markdown,gherkin,formatter
Author-email: Emilio Romero <emilio.romero1989@gmail.com>
Requires-Python: >=3.7
Classifier: Topic :: Documentation
Classifier: Topic :: Text Processing :: Markup
Classifier: Programming Language :: Python :: 3
Classifier: Programming Language :: Python :: 3.7
Classifier: Programming Language :: Python :: 3.8
Classifier: Programming Language :: Python :: 3.9
Classifier: Programming Language :: Python :: 3.10
Classifier: Programming Language :: Python :: 3.11
License-File: LICENSE
Requires-Dist: mdformat >=0.3.0
Requires-Dist: reformat-gherkin
Project-URL: Homepage, https://github.com/emiliogrv/mdformat-gherkin
